pergamos/__init__.py
pergamos/css.py
pergamos/html.py
pergamos/js.py
pergamos/objects.py
pergamos/utils.py
pergamos/wrappers.py
pergamos/css/default.css
pergamos-0.0.8.dist-info/METADATA
pergamos-0.0.8.dist-info/WHEEL
pergamos-0.0.8.dist-info/entry_points.txt
pergamos-0.0.8.dist-info/top_level.txt
pergamos-0.0.8.dist-info/RECORD
