Metadata-Version: 2.4
Name: pergamos
Version: 0.0.8
Summary: A lightweight dynamic module for automatic HTML reporting
Author-email: Manu B Valentin <manuel.blanco.valentin@gmail.com>
Project-URL: Homepage, https://github.com/manuelblancovalentin/pergamos
Project-URL: Repository, https://github.com/manuelblancovalentin/pergamos
Project-URL: Issues, https://github.com/manuelblancovalentin/pergamos/issues
Keywords: html,markdown,reporting,automation,dynamic,syntax-highlighting
Classifier: License :: OSI Approved :: MIT License
Classifier: Programming Language :: Python
Classifier: Programming Language :: Python :: 3
Classifier: Development Status :: 4 - Beta
Classifier: Intended Audience :: Developers
Classifier: Topic :: Software Development :: Libraries :: Python Modules
Classifier: Topic :: Text Processing :: Markup :: HTML
Requires-Python: >=3.10
Requires-Dist: feedparser>=5.2.0
Requires-Dist: html2text
Requires-Dist: markdown>=3.3
Requires-Dist: pygments
Requires-Dist: numpy
Requires-Dist: pandas
Requires-Dist: matplotlib
Requires-Dist: mpld3
Requires-Dist: tomli; python_version < "3.11"
Provides-Extra: dev
Requires-Dist: black; extra == "dev"
Requires-Dist: bumpver; extra == "dev"
Requires-Dist: isort; extra == "dev"
Requires-Dist: pip-tools; extra == "dev"
Requires-Dist: pytest; extra == "dev"
